pychatbotlib/__init__.py
pychatbotlib/pychatbotlib.py
pychatbotlib/sqlite3_wrapper.py
pychatbotlib-1.0.1.dist-info/METADATA
pychatbotlib-1.0.1.dist-info/RECORD
pychatbotlib-1.0.1.dist-info/WHEEL
pychatbotlib-1.0.1.dist-info/top_level.txt
