Metadata-Version: 2.1
Name: pychatbotlib
Version: 1.0.1
Summary: Library for creating chatbots
Home-page: https://github.com/1M50RRY/pychatbotlib
Author: ims0rry
Author-email: dmr0@protonmail.com
License: UNKNOWN
Platform: UNKNOWN
Classifier: Programming Language :: Python :: 3
Classifier: License :: OSI Approved :: MIT License
Classifier: Operating System :: OS Independent
